MANIFEST.in
README.md
setup.py
infestor/__init__.py
infestor/main.py
infestor/utils.py
infestor/web.py
infestor.egg-info/PKG-INFO
infestor.egg-info/SOURCES.txt
infestor.egg-info/dependency_links.txt
infestor.egg-info/entry_points.txt
infestor.egg-info/not-zip-safe
infestor.egg-info/requires.txt
infestor.egg-info/top_level.txt
infestor/templates/base.html
infestor/templates/create_account.html
infestor/templates/gift_codes.html
infestor/templates/login.html
infestor/templates/success.html