Metadata-Version: 1.0
Name: infestor
Version: 0.1.3
Summary: CLI app to claim and create discounted accounts on the STEEM blockchain.
Home-page: http://github.com/emre/transmitter
Author: emre yilmaz
Author-email: mail@emreyilmaz.me
License: MIT
Platform: UNKNOWN
